{
  "characterId": 17,
  "rarity": 2,
  "attribute": "happy",
  "levelLimit": 30,
  "resourceSetName": "res017086",
  "sdResourceName": "sd017086",
  "costumeId": 2369,
  "gachaText": [
    null,
    null,
    null,
    null,
    null
  ],
  "prefix": [
    "トラベリング・ウェイ",
    "Travelling Way",
    null,
    null,
    null
  ],
  "releasedAt": [
    "1778392800000",
    null,
    null,
    null,
    null
  ],
  "skillName": [
    "ラフに楽しもう♪",
    "Casually Havin' Fun ♪",
    null,
    null,
    null
  ],
  "skillId": 23,
  "source": null,
  "type": "event",
  "stat": {
    "1": {
      "performance": 2178,
      "technique": 2420,
      "visual": 1812
    },
    "2": {
      "performance": 2237,
      "technique": 2485,
      "visual": 1861
    },
    "3": {
      "performance": 2300,
      "technique": 2555,
      "visual": 1913
    },
    "4": {
      "performance": 2367,
      "technique": 2629,
      "visual": 1968
    },
    "5": {
      "performance": 2437,
      "technique": 2707,
      "visual": 2027
    },
    "6": {
      "performance": 2511,
      "technique": 2790,
      "visual": 2089
    },
    "7": {
      "performance": 2589,
      "technique": 2877,
      "visual": 2154
    },
    "8": {
      "performance": 2671,
      "technique": 2968,
      "visual": 2222
    },
    "9": {
      "performance": 2757,
      "technique": 3064,
      "visual": 2294
    },
    "10": {
      "performance": 2847,
      "technique": 3164,
      "visual": 2369
    },
    "11": {
      "performance": 2941,
      "technique": 3268,
      "visual": 2447
    },
    "12": {
      "performance": 3039,
      "technique": 3377,
      "visual": 2528
    },
    "13": {
      "performance": 3141,
      "technique": 3490,
      "visual": 2613
    },
    "14": {
      "performance": 3247,
      "technique": 3607,
      "visual": 2701
    },
    "15": {
      "performance": 3357,
      "technique": 3729,
      "visual": 2792
    },
    "16": {
      "performance": 3470,
      "technique": 3855,
      "visual": 2886
    },
    "17": {
      "performance": 3587,
      "technique": 3985,
      "visual": 2984
    },
    "18": {
      "performance": 3708,
      "technique": 4120,
      "visual": 3085
    },
    "19": {
      "performance": 3833,
      "technique": 4259,
      "visual": 3189
    },
    "20": {
      "performance": 3962,
      "technique": 4402,
      "visual": 3296
    },
    "21": {
      "performance": 4095,
      "technique": 4550,
      "visual": 3407
    },
    "22": {
      "performance": 4232,
      "technique": 4702,
      "visual": 3521
    },
    "23": {
      "performance": 4373,
      "technique": 4858,
      "visual": 3638
    },
    "24": {
      "performance": 4518,
      "technique": 5019,
      "visual": 3758
    },
    "25": {
      "performance": 4667,
      "technique": 5184,
      "visual": 3882
    },
    "26": {
      "performance": 4819,
      "technique": 5353,
      "visual": 4009
    },
    "27": {
      "performance": 4975,
      "technique": 5527,
      "visual": 4139
    },
    "28": {
      "performance": 5135,
      "technique": 5705,
      "visual": 4272
    },
    "29": {
      "performance": 5299,
      "technique": 5887,
      "visual": 4409
    },
    "30": {
      "performance": 5467,
      "technique": 6074,
      "visual": 4549
    }
  }
}